{
    "home": {
        "TERMINAL": {
            "port": 8022,
            "title": "Terminal",
            "description": "Full-fledged WEB-based Command Line Interface",
            "image": "assets/home/terminal.png"
        },
        "FILEBROWSER": {
            "port": 8023,
            "title": "Filebrowser",
            "name": "File Browser",
            "description": "Browse, upload and download files and folders to and from the workspace",
            "image": "assets/home/Filebrowser.png"
        }
    },
    "my_apps": {
        "PORT_8029": {
            "port": 8029,
            "title": "My app on port 8029",
            "description": "Start any app or service that listens on port 8029. Use this link for quick access",
            "image": "port-8029.png"
        },
        "PORT_8030": {
            "port": 8030,
            "title": "My app on port 8030",
            "description": "Start any app or service that listens on port 8030. Use this link for quick access",
            "image": "port-8030.png"
        }
    }
}